{
  "unversionedId": "admin/upgrade",
  "id": "version-4.12.1/admin/upgrade",
  "title": "Upgrade",
  "description": "If you have questions about upgrades (or need help), please feel free to reach out to us by mailing list or Slack Channel.",
  "source": "@site/versioned_docs/version-4.12.1/admin/upgrade.md",
  "sourceDirName": "admin",
  "slug": "/admin/upgrade",
  "permalink": "/docs/4.12.1/admin/upgrade",
  "tags": [],
  "version": "4.12.1",
  "frontMatter": {
    "id": "upgrade",
    "title": "Upgrade"
  },
  "sidebar": "version-4.12.1/docsSidebar",
  "previous": {
    "title": "Metric collection",
    "permalink": "/docs/4.12.1/admin/metrics"
  },
  "next": {
    "title": "BookKeeper Admin REST API",
    "permalink": "/docs/4.12.1/admin/http"
  }
}